LICENSE
MANIFEST.in
README.md
README.pypi
pyproject.toml
requirements.txt
setup.py
Orange3_elementwise.egg-info/PKG-INFO
Orange3_elementwise.egg-info/SOURCES.txt
Orange3_elementwise.egg-info/dependency_links.txt
Orange3_elementwise.egg-info/entry_points.txt
Orange3_elementwise.egg-info/namespace_packages.txt
Orange3_elementwise.egg-info/not-zip-safe
Orange3_elementwise.egg-info/requires.txt
Orange3_elementwise.egg-info/top_level.txt
orangecontrib/__init__.py
orangecontrib/elementwise/__init__.py
orangecontrib/elementwise/widgets/__init__.py
orangecontrib/elementwise/widgets/owoperations.py
orangecontrib/elementwise/widgets/owwhere.py
orangecontrib/elementwise/widgets/components/__init__.py
orangecontrib/elementwise/widgets/components/widgets/__init__.py
orangecontrib/elementwise/widgets/components/widgets/textlineedit.py
orangecontrib/elementwise/widgets/icons/category.svg
orangecontrib/elementwise/widgets/icons/operations.svg
orangecontrib/elementwise/widgets/icons/where.svg